libfast/__init__.py
libfast/fcfg.py
libfast/fcmd.py
libfast/fconst.py
libfast/fio.py
libfast/flog.py
libfast/fmd5.py
libfast/frenew.py
libfast/fsqlite.py
libfast/fsqlite1.py
libfast/fxml.py
libfast/test.py
libfast/decorator/__init__.py
libfast/decorator/singleton.py
fast_stl-1.0.1.dist-info/LICENSE.txt
fast_stl-1.0.1.dist-info/METADATA
fast_stl-1.0.1.dist-info/WHEEL
fast_stl-1.0.1.dist-info/top_level.txt
fast_stl-1.0.1.dist-info/RECORD
